{
  "type": "FeatureCollection",
  "features": [
    {
      "type": "Feature",
      "properties": {
        "station": "1"
      },
      "geometry": {
        "type": "Point",
        "coordinates": [
          -0.17297029495239258,
          51.533255921019375
        ]
      }
    },
    {
      "type": "Feature",
      "properties": {
        "station": "13"
      },
      "geometry": {
        "type": "Point",
        "coordinates": [
          -0.12402534484863281,
          51.52997220303645
        ]
      }
    },
    {
      "type": "Feature",
      "properties": {
        "station": "46"
      },
      "geometry": {
        "type": "Point",
        "coordinates": [
          -0.15751004219055176,
          51.522095653950174
        ]
      }
    },
    {
      "type": "Feature",
      "properties": {
        "station": "67"
      },
      "geometry": {
        "type": "Point",
        "coordinates": [
          -0.12033462524414064,
          51.51760941705477
        ]
      }
    },
    {
      "type": "Feature",
      "properties": {
        "station": "74"
      },
      "geometry": {
        "type": "Point",
        "coordinates": [
          -0.1776266098022461,
          51.51440469156112
        ]
      }
    },
    {
      "type": "Feature",
      "properties": {
        "station": "79"
      },
      "geometry": {
        "type": "Point",
        "coordinates": [
          -0.15022516250610352,
          51.51426447967265
        ]
      }
    },
    {
      "type": "Feature",
      "properties": {
        "station": "89"
      },
      "geometry": {
        "type": "Point",
        "coordinates": [-0.08896266128394359, 51.513426265033644]
      }
    },
    {
      "type": "Feature",
      "properties": {
        "station": "93"
      },
      "geometry": {
        "type": "Point",
        "coordinates": [
          -0.18280863761901855,
          51.51055204602377
        ]
      }
    },
    {
      "type": "Feature",
      "properties": {
        "station": "111"
      },
      "geometry": {
        "type": "Point",
        "coordinates": [
          -0.14200687408447266,
          51.50713981232172
        ]
      }
    },
    {
      "type": "Feature",
      "properties": {
        "station": "128"
      },
      "geometry": {
        "type": "Point",
        "coordinates": [-0.10093256072775603, 51.49559003189688]
      }
    },
    {
      "type": "Feature",
      "properties": {
        "station": "140"
      },
      "geometry": {
        "type": "Point",
        "coordinates": [-0.12617160266000838, 51.50091495550987]
      }
    },
    {
      "type": "Feature",
      "properties": {
        "station": "153"
      },
      "geometry": {
        "type": "Point",
        "coordinates": [-0.1447986359501101, 51.496704741184345]
      }
    },
    {
      "type": "Feature",
      "properties": {
        "station": "163"
      },
      "geometry": {
        "type": "Point",
        "coordinates": [-0.17452320999393578, 51.49385089019748]
      }
    },
    {
      "type": "Feature",
      "properties": {
        "station": "185"
      },
      "geometry": {
        "type": "Point",
        "coordinates": [-0.12365359753113125, 51.48645682171511]
      }
    }
  ]
}
